LuFeixuechengQianduankaifaFix1/README.md
LuFeixuechengQianduankaifaFix1/__init__.py
LuFeixuechengQianduankaifaFix1/__main__.py
LuFeixuechengQianduankaifaFix1/file.epub
LuFeixuechengQianduankaifaFix1/index.html
LuFeixuechengQianduankaifaFix1/css/__init__.py
LuFeixuechengQianduankaifaFix1/css/annotations.css
LuFeixuechengQianduankaifaFix1/css/main.css
LuFeixuechengQianduankaifaFix1/css/normalize.css
LuFeixuechengQianduankaifaFix1/css/popup.css
LuFeixuechengQianduankaifaFix1/font/__init__.py
LuFeixuechengQianduankaifaFix1/font/fontello.eot
LuFeixuechengQianduankaifaFix1/font/fontello.svg
LuFeixuechengQianduankaifaFix1/font/fontello.ttf
LuFeixuechengQianduankaifaFix1/font/fontello.woff
LuFeixuechengQianduankaifaFix1/img/__init__.py
LuFeixuechengQianduankaifaFix1/img/annotator-glyph-sprite.png
LuFeixuechengQianduankaifaFix1/img/annotator-icon-sprite.png
LuFeixuechengQianduankaifaFix1/img/apple-touch-icon.png
LuFeixuechengQianduankaifaFix1/img/cancelfullscreen.png
LuFeixuechengQianduankaifaFix1/img/close.png
LuFeixuechengQianduankaifaFix1/img/fullscreen.png
LuFeixuechengQianduankaifaFix1/img/loader.gif
LuFeixuechengQianduankaifaFix1/img/menu-icon.png
LuFeixuechengQianduankaifaFix1/img/save.png
LuFeixuechengQianduankaifaFix1/img/saved.png
LuFeixuechengQianduankaifaFix1/img/settings-s.png
LuFeixuechengQianduankaifaFix1/img/settings.png
LuFeixuechengQianduankaifaFix1/img/star.png
LuFeixuechengQianduankaifaFix1/js/__init__.py
LuFeixuechengQianduankaifaFix1/js/epub.js
LuFeixuechengQianduankaifaFix1/js/epub.min.js
LuFeixuechengQianduankaifaFix1/js/epub.min.map
LuFeixuechengQianduankaifaFix1/js/hooks.min.js
LuFeixuechengQianduankaifaFix1/js/hooks.min.map
LuFeixuechengQianduankaifaFix1/js/reader.js
LuFeixuechengQianduankaifaFix1/js/reader.js.map
LuFeixuechengQianduankaifaFix1/js/reader.min.js
LuFeixuechengQianduankaifaFix1/js/reader.min.map
LuFeixuechengQianduankaifaFix1/js/hooks/__init__.py
LuFeixuechengQianduankaifaFix1/js/hooks/extensions/__init__.py
lu_feixuecheng_qianduankaifa_fix1-2025.3.25.1.dist-info/METADATA
lu_feixuecheng_qianduankaifa_fix1-2025.3.25.1.dist-info/WHEEL
lu_feixuecheng_qianduankaifa_fix1-2025.3.25.1.dist-info/entry_points.txt
lu_feixuecheng_qianduankaifa_fix1-2025.3.25.1.dist-info/top_level.txt
lu_feixuecheng_qianduankaifa_fix1-2025.3.25.1.dist-info/RECORD
